messagev/__init__.py
messagev/auth/auth_pb2.py
messagev/base/base_pb2.py
messagev/commands/backupdb_pb2.py
messagev/commands/command_pb2.py
messagev/commands/configv_pb2.py
messagev/commands/info_pb2.py
messagev/commands/restic_pb2.py
messagev/commands/status_pb2.py
messagev/commands/workflow_pb2.py
messagev-0.0.27.dist-info/AUTHORS.rst
messagev-0.0.27.dist-info/LICENSE
messagev-0.0.27.dist-info/METADATA
messagev-0.0.27.dist-info/WHEEL
messagev-0.0.27.dist-info/top_level.txt
messagev-0.0.27.dist-info/RECORD
