Metadata-Version: 2.1
Name: messagev
Version: 0.0.27
Summary: MessageV: the python files generated for consuming the OrchestSh API
Home-page: 
Author: Vauxoo
Author-email: Vauxoo <info@vauxoo.com>
License: Copyright (c) 2019, Vauxoo
Keywords: messagev
Classifier: Programming Language :: Python :: 3
Classifier: License :: OSI Approved :: BSD License
Classifier: Operating System :: OS Independent
Classifier: Development Status :: 2 - Pre-Alpha
Classifier: Intended Audience :: Developers
Classifier: Natural Language :: English
Requires-Python: >=3.6
License-File: LICENSE
License-File: AUTHORS.rst
Requires-Dist: grpcio==1.62.1
Requires-Dist: protobuf==5.26.0
